Workbook

Sheet Dashboard
A1: STACK POLICY INTELLIGENCE — MASTER DATA
A4: Metric | B4: Value | D4: Score Band | E4: Count
A5: States Tracked | B5: =COUNTA('State Scores'!A2:A51) -> 50 | D5: Favorable | E5: =COUNTIF('State Scores'!G2:G51,">=80") -> 4
A6: Favorable Today | B6: =COUNTIF('State Scores'!G2:G51,">=80") -> 4 | D6: Moderate | E6: =COUNTIFS('State Scores'!G2:G51,">=60",'State Scores'!G2:G51,"<80") -> 17
A7: High Forward Risk | B7: =COUNTIF('State Scores'!I2:I51,"HIGH") -> 17 | D7: Challenging | E7: =COUNTIFS('State Scores'!G2:G51,">=40",'State Scores'!G2:G51,"<60") -> 24
A8: High Confidence | B8: =COUNTIF('State Scores'!J2:J51,"High") -> 20 | D8: Restrictive | E8: =COUNTIF('State Scores'!G2:G51,"<40") -> 5
D9: Total | E9: =SUM(E5:E8) -> 50
A10: Average Policy Score | B10: =AVERAGE('State Scores'!G2:G51) -> 57.66
A11: Scores in Dashboard | B11: =SUM(E5:E8) -> 50
A12: Reconciliation | B12: =IF(B5=B11,"OK","CHECK") -> OK
A13: Publication Guardrail | B13: Rule
A14: Current Score | B14: Only operative/current conditions; future proposals belong in Trend / Forward Risk.
A15: Local | B15: HeatMap raw index is stored separately from analyst Community Score until HeatMap confirms scale.
A16: Change Log | B16: Every published score change should record old/new values, reason, source and event ID.

Sheet State Scores
A1: State | B1: Abbr | C1: Power & Energy (35%) | D1: Water (15%) | E1: Policy & Regulatory Environment (25%) | F1: Community Sentiment (25%) | G1: Overall Score | H1: Trend | I1: Forward Policy Risk | J1: Confidence | K1: Research Status | L1: STACK Posture | M1: Policy Thesis
A2: Alabama | B2: AL | C2: 0 | D2: 0 | E2: 0 | F2: 0 | G2: =ROUND(20*(0.35*C2+0.15*D2+0.25*E2+0.25*F2),1) -> 0 | H2: ↓ | I2: MODERATE | J2: High | K2: Calibrated | L2: B — SELECTIVE | M2: Low-regulation state with favorable incentives, but local moratoria and utility requirements are rising.
A3: Alaska | B3: AK | C3: 2 | D3: 4 | E3: 3.5 | F3: 3 | G3: =ROUND(20*(0.35*C3+0.15*D3+0.25*E3+0.25*F3),1) -> 58.5 | H3: → | I3: MODERATE | J3: Low | K3: Calibrated | L3: C — LIMIT | M3: Supportive posture and no statewide SUT, but fragmented grid and infrastructure constraints dominate.
A4: Arizona | B4: AZ | C4: 2.5 | D4: 2.5 | E4: 2 | F4: 2.5 | G4: =ROUND(20*(0.35*C4+0.15*D4+0.25*E4+0.25*F4),1) -> 47.5 | H4: ↓↓ | I4: HIGH | J4: High | K4: Calibrated | L4: C — LIMIT | M4: Three-year incentive moratorium, new large-load authority, and growing local restrictions materially weaken the market.
A5: Arkansas | B5: AR | C5: 3.5 | D5: 4 | E5: 4.5 | F5: 3.5 | G5: =ROUND(20*(0.35*C5+0.15*D5+0.25*E5+0.25*F5),1) -> 76.5 | H5: → | I5: MODERATE | J5: Low | K5: Calibrated | L5: A/B — SELECTIVE | M5: Favorable incentive construct and state support; local pushback is emerging and source coverage is limited.
A6: California | B6: CA | C6: 2 | D6: 1.5 | E6: 2 | F6: 1.5 | G6: =ROUND(20*(0.35*C6+0.15*D6+0.25*E6+0.25*F6),1) -> 36 | H6: ↓↓ | I6: HIGH | J6: Medium | K6: Calibrated | L6: D — PAUSE | M6: No statewide SUT incentive, restrictive environmental policy, and accelerating local bans/moratoria.
A7: Colorado | B7: CO | C7: 2.5 | D7: 2.5 | E7: 2 | F7: 2 | G7: =ROUND(20*(0.35*C7+0.15*D7+0.25*E7+0.25*F7),1) -> 45 | H7: ↓ | I7: ELEVATED | J7: Medium | K7: Calibrated | L7: C — LIMIT | M7: No data-center SUT incentive and growing local zoning/moratorium activity; 2026 incentive legislation failed.
A8: Connecticut | B8: CT | C8: 3 | D8: 3 | E8: 2.5 | F8: 3 | G8: =ROUND(20*(0.35*C8+0.15*D8+0.25*E8+0.25*F8),1) -> 57.5 | H8: ↓ | I8: ELEVATED | J8: Low | K8: Calibrated | L8: C — LIMIT | M8: Current environment is mixed; attempted closure of the incentive program signals weakening political support.
A9: Delaware | B9: DE | C9: 2 | D9: 3.5 | E9: 3 | F9: 3 | G9: =ROUND(20*(0.35*C9+0.15*D9+0.25*E9+0.25*F9),1) -> 54.5 | H9: ↓ | I9: ELEVATED | J9: Medium | K9: Calibrated | L9: C — LIMIT | M9: New large-load tariff law shifts infrastructure costs and long-term obligations to large users.
A10: Florida | B10: FL | C10: 3.5 | D10: 3 | E10: 3 | F10: 2 | G10: =ROUND(20*(0.35*C10+0.15*D10+0.25*E10+0.25*F10),1) -> 58.5 | H10: ↓ | I10: ELEVATED | J10: Medium | K10: Calibrated | L10: B — SELECTIVE | M10: State preserves local authority while local moratoria spread across major jurisdictions.
A11: Georgia | B11: GA | C11: 2.5 | D11: 3 | E11: 4 | F11: 1.5 | G11: =ROUND(20*(0.35*C11+0.15*D11+0.25*E11+0.25*F11),1) -> 54 | H11: ↓ | I11: ELEVATED | J11: High | K11: Calibrated | L11: C — LIMIT | M11: Strong tax incentive is offset by adverse power terms and exceptionally broad local opposition.
A12: Hawaii | B12: HI | C12: 1.5 | D12: 4 | E12: 2.5 | F12: 3 | G12: =ROUND(20*(0.35*C12+0.15*D12+0.25*E12+0.25*F12),1) -> 50 | H12: → | I12: MODERATE | J12: Low | K12: Calibrated | L12: D — PAUSE | M12: Policy scrutiny is limited today, but isolated grids create a structurally difficult large-load environment.
A13: Idaho | B13: ID | C13: 4 | D13: 3 | E13: 4 | F13: 3.5 | G13: =ROUND(20*(0.35*C13+0.15*D13+0.25*E13+0.25*F13),1) -> 74.5 | H13: ↓ | I13: ELEVATED | J13: Medium | K13: Calibrated | L13: A/B — SELECTIVE | M13: Full SUT exemption and workable power backdrop remain attractive, while water and legislative scrutiny are increasing.
... A51: Wyoming | B51: WY | C51: 4.5 | D51: 4 | E51: 4.5 | F51: 4.5 | G51: =ROUND(20*(0.35*C51+0.15*D51+0.25*E51+0.25*F51),1) -> 88.5 | H51: ↓ | I51: ELEVATED | J51: High | K51: Calibrated | L51: A — PRIORITIZE | M51: Full SUT exemption, strong BTM flexibility and receptive development conditions remain attractive; 2027 recommendations create forward risk.

Sheet Validation Lists
A1: Trend | B1: Forward Risk | C1: Confidence | D1: Research Status | E1: STACK Posture | F1: Direction | G1: Event Status | H1: County Tier
A2: ↑↑ | B2: LOW | C2: High | D2: Calibrated | E2: A — PRIORITIZE | F2: Positive | G2: Enacted | H2: Tier 1 — Established
A3: ↑ | B3: MODERATE | C3: Medium | D3: Researched | E3: A/B — SELECTIVE | F3: Negative | G3: Active | H3: Tier 2 — Plausible
A4: → | B4: ELEVATED | C4: Low | D4: Provisional | E4: B — SELECTIVE | F4: Mixed | G4: Proposed | H4: Tier 3 — Monitor
A5: ↓ | B5: HIGH | E5: C — LIMIT | F5: Neutral | G5: Failed
A6: ↓↓ | E6: D — PAUSE | G6: Expected
G7: Monitoring

Sheet County Local
A1: State | B1: County | C1: County FIPS | D1: County Tier | E1: Use in State Rollup? | F1: Market Relevance Weight | G1: HeatMap Opposition Index | H1: Community Score (1-5) | I1: Local Policy & Entitlements (1-5) | J1: Development Precedent (1-5) | K1: Raw County Local Score | L1: Rounded County Local Score | M1: Contested DC Projects | N1: Operating DC MW | O1: Planned / Construction DC MW | P1: Moratoria / Ordinance Signal | Q1: HeatMap Date | R1: Confidence | S1: Analyst Rationale | T1: Source ID | U1: Source Detail | V1: Notes
A2: California | B2: Los Angeles County | D2: Tier 1 — Established | E2: Yes | F2: 1 | G2: 41 | H2: 3.5 | I2: 2.5 | J2: 5 | K2: =IF(COUNTA(H2:J2)=3,H2*40%+I2*50%+J2*10%,"") -> 3.15 | L2: =IF(K2="","",MROUND(K2,0.5)) -> 3 | M2: 4 | N2: 239 | O2: 32 | P2: HeatMap detected restrictive zoning / moratoriums in the area | Q2: 46277 | R2: High | S2: Moderate modeled opposition (Index 41) is offset by substantial operating/planned data-center precedent, while documented restrictive zoning/moratorium signals reduce the policy component. | T2: SRC-HEATMAP-LA | U2: HeatMap Risk Report – Los Angeles County, California (9/12/2026)
A3: Virginia | B3: Loudoun County | D3: Tier 1 — Established | E3: Yes | F3: 1 | K3: =IF(COUNTA(H3:J3)=3,H3*40%+I3*50%+J3*10%,"") | L3: =IF(K3="","",MROUND(K3,0.5)) | R3: Low | V3: Awaiting HeatMap county report/export
A4: Arizona | B4: Maricopa County | D4: Tier 1 — Established | E4: Yes | F4: 1 | K4: =IF(COUNTA(H4:J4)=3,H4*40%+I4*50%+J4*10%,"") | L4: =IF(K4="","",MROUND(K4,0.5)) | R4: Low | V4: Awaiting HeatMap county report/export
A5: Texas | B5: Dallas County | D5: Tier 1 — Established | E5: Yes | F5: 1 | K5: =IF(COUNTA(H5:J5)=3,H5*40%+I5*50%+J5*10%,"") | L5: =IF(K5="","",MROUND(K5,0.5)) | R5: Low | V5: Awaiting HeatMap county report/export
A6: Texas | B6: Tarrant County | D6: Tier 1 — Established | E6: Yes | F6: 1 | K6: =IF(COUNTA(H6:J6)=3,H6*40%+I6*50%+J6*10%,"") | L6: =IF(K6="","",MROUND(K6,0.5)) | R6: Low | V6: Awaiting HeatMap county report/export
A7: Georgia | B7: Douglas County | D7: Tier 1 — Established | E7: Yes | F7: 1 | K7: =IF(COUNTA(H7:J7)=3,H7*40%+I7*50%+J7*10%,"") | L7: =IF(K7="","",MROUND(K7,0.5)) | R7: Low | V7: Awaiting HeatMap county report/export
A8: Georgia | B8: Fulton County | D8: Tier 1 — Established | E8: Yes | F8: 1 | K8: =IF(COUNTA(H8:J8)=3,H8*40%+I8*50%+J8*10%,"") | L8: =IF(K8="","",MROUND(K8,0.5)) | R8: Low | V8: Awaiting HeatMap county report/export
A9: Ohio | B9: Franklin County | D9: Tier 1 — Established | E9: Yes | F9: 1 | K9: =IF(COUNTA(H9:J9)=3,H9*40%+I9*50%+J9*10%,"") | L9: =IF(K9="","",MROUND(K9,0.5)) | R9: Low | V9: Awaiting HeatMap county report/export
A10: Illinois | B10: Cook County | D10: Tier 1 — Established | E10: Yes | F10: 1 | K10: =IF(COUNTA(H10:J10)=3,H10*40%+I10*50%+J10*10%,"") | L10: =IF(K10="","",MROUND(K10,0.5)) | R10: Low | V10: Awaiting HeatMap county report/export
A11: Oregon | B11: Washington County | D11: Tier 1 — Established | E11: Yes | F11: 1 | K11: =IF(COUNTA(H11:J11)=3,H11*40%+I11*50%+J11*10%,"") | L11: =IF(K11="","",MROUND(K11,0.5)) | R11: Low | V11: Awaiting HeatMap county report/export
A12: California | B12: Santa Clara County | D12: Tier 1 — Established | E12: Yes | F12: 1 | K12: =IF(COUNTA(H12:J12)=3,H12*40%+I12*50%+J12*10%,"") | L12: =IF(K12="","",MROUND(K12,0.5)) | R12: Low | V12: Awaiting HeatMap county report/export
A13: Nevada | B13: Clark County | D13: Tier 1 — Established | E13: Yes | F13: 1 | K13: =IF(COUNTA(H13:J13)=3,H13*40%+I13*50%+J13*10%,"") | L13: =IF(K13="","",MROUND(K13,0.5)) | R13: Low | V13: Awaiting HeatMap county report/export
A14: New Jersey | B14: Middlesex County | D14: Tier 1 — Established | E14: Yes | F14: 1 | K14: =IF(COUNTA(H14:J14)=3,H14*40%+I14*50%+J14*10%,"") | L14: =IF(K14="","",MROUND(K14,0.5)) | R14: Low | V14: Awaiting HeatMap county report/export

Sheet Policy Events
A1: Event ID | B1: Event Date | C1: Target Window | D1: State | E1: Abbr | F1: Level | G1: Locality | H1: Event Type | I1: Category | J1: Status | K1: Direction | L1: Severity | M1: Headline | N1: Detail | O1: Score Dimension | P1: Score Impact | Q1: Trend Impact | R1: Forward Risk Impact | S1: Source ID | T1: Source Locator | U1: Source URL | V1: Last Verified | W1: Notes
A2: EVT-0001 | B2: 46261 | C2: 313 | D2: New Jersey | E2: NJ | F2: State | H2: Current Change | I2: Incentives & Tax | J2: Enacted | K2: Negative | L2: High | M2: Governor signed the End Data Center Tax Credits Act | N2: Eliminates the remaining $250 million in uncommitted Next New Jersey AI/data-center tax credits and redirects the funds. | O2: Incentives & Tax | Q2: ↓↓ | S2: SRC-MULTISTATE-AUG26 | T2: Multistate report, Aug. 2026
A3: EVT-0002 | B3: 46260 | C3: 313 | D3: Delaware | E3: DE | F3: State | H3: Current Change | I3: Power & Energy | J3: Enacted | K3: Negative | L3: High | M3: HB 233 signed; large-load tariff now required | N3: Requires large users to bear dedicated infrastructure costs through a large-load tariff and allows the PSC to deny connections if ratepayer protections are insufficient. | O3: Power & Energy | Q3: ↓↓ | S3: SRC-MULTISTATE-AUG26 | T3: Multistate report, Aug. 2026
A4: EVT-0003 | B4: 46252 | C4: 313 | D4: Pennsylvania | E4: PA | F4: State | H4: Current Change | I4: Political & Regulatory | J4: Enacted | K4: Negative | L4: High | M4: Executive Order 2026-05 makes GRID requirements binding | N4: Conditions permitting and tax incentives on GRID compliance, removes AI data centers from permit fast track, and requires local approval before state permits. | O4: Political & Regulatory | Q4: ↓↓ | S4: SRC-MULTISTATE-AUG26 | T4: Multistate report, Aug. 2026
A5: EVT-0004 | B5: 46240 | C5: 313 | D5: Kentucky | E5: KY | F5: State | H5: Current Change | I5: Political & Regulatory | J5: Enacted | K5: Negative | L5: High | M5: Executive Order 2026-494 raises permitting bar | N5: Directs agencies to deny permits that harm ratepayers or environmental resources and requires developers to submit energy plans. | O5: Political & Regulatory | Q5: ↓↓ | S5: SRC-MULTISTATE-AUG26 | T5: Multistate report, Aug. 2026
A6: EVT-0005 | B6: 46237 | C6: 313 | D6: Texas | E6: TX | F6: State | H6: Current Change | I6: Power & Energy | J6: Enacted | K6: Negative | L6: High | M6: ERCOT interconnection audit halts advancing connections | N6: Governor directed PUCT and ERCOT to verify all data centers advancing through the interconnection process; noncompliant projects can be denied connection. | O6: Power & Energy | Q6: ↓↓ | S6: SRC-MULTISTATE-AUG26 | T6: Multistate report, Aug. 2026
A7: EVT-0006 | B7: 46234 | C7: 313 | D7: Virginia | E7: VA | F7: State | H7: Current Change | I7: Power & Energy | J7: Enacted | K7: Negative | L7: High | M7: SCC assigns dedicated transmission costs to large-load data centers | N7: Large-load customers must pay for transmission facilities built solely to serve them, establishing a stronger cost-causation precedent. | O7: Power & Energy | Q7: ↓↓ | S7: SRC-MULTISTATE-AUG26 | T7: Multistate report, Aug. 2026
A8: EVT-0007 | B8: 46224 | C8: 313 | D8: Nebraska | E8: NE | F8: State | H8: Current Change | I8: Incentives & Tax | J8: Enacted | K8: Negative | L8: High | M8: Governor ends data-center access to ImagiNE Nebraska incentives | N8: Executive order removes incentive eligibility and creates an interagency review and data-center task force. | O8: Incentives & Tax | Q8: ↓↓ | S8: SRC-MULTISTATE-AUG26 | T8: Multistate report, Aug. 2026
A9: EVT-0008 | B9: 46217 | C9: 313 | D9: New York | E9: NY | F9: State | H9: Current Change | I9: Political & Regulatory | J9: Enacted | K9: Negative | L9: High | M9: Executive Order 62 creates one-year hyperscale permitting moratorium | N9: Pauses state environmental permits for hyperscale facilities of 50 MW or more while agencies develop a new regulatory framework. | O9: Political & Regulatory | Q9: ↓↓ | S9: SRC-MULTISTATE-AUG26 | T9: Multistate report, Aug. 2026
A10: EVT-0009 | B10: 46371 | D10: Virginia | E10: VA | F10: State | H10: Forward Catalyst | I10: Political & Regulatory | J10: Expected | K10: Negative | L10: High | M10: Joint Subcommittee tax-policy recommendations due | N10: Recommendations could reshape the data-center sales/use tax framework after the 2026 budget compromise. | O10: Political & Regulatory | Q10: ↓ | R10: ELEVATED | S10: SRC-MULTISTATE-AUG26 | T10: Multistate report, Aug. 2026
A11: EVT-0010 | B11: 46406 | D11: New Mexico | E11: NM | F11: State | H11: Forward Catalyst | I11: Political & Regulatory | J11: Expected | K11: Negative | L11: High | M11: Statewide moratorium proposal expected in 2027 session | N11: Sponsors have previewed a two-to-five-year moratorium framework and companion legislation targeting the microgrid pathway. | O11: Political & Regulatory | Q11: ↓ | R11: HIGH | S11: SRC-MULTISTATE-AUG26 | T11: Multistate report, Aug. 2026
A12: EVT-0011 | C12: 2027-session | D12: Texas | E12: TX | F12: State | H12: Forward Catalyst | I12: Political & Regulatory | J12: Expected | K12: Negative | L12: High | M12: Incentive repeal and new operating guardrails expected | N12: Governor has pledged to pursue sales-tax exemption repeal plus water-efficient cooling, added generation and siting requirements. | O12: Political & Regulatory | Q12: ↓ | R12: HIGH | S12: SRC-MULTISTATE-AUG26 | T12: Multistate report, Aug. 2026
A13: EVT-0012 | C13: 2027-session | D13: Wyoming | E13: WY | F13: State | H13: Forward Catalyst | I13: Political & Regulatory | J13: Expected | K13: Negative | L13: High | M13: Policy recommendations from Governor-directed review | N13: The 2026 executive review is expected to inform legislation on water, power and responsible data-center development. | O13: Political & Regulatory | Q13: ↓ | R13: ELEVATED | S13: SRC-MULTISTATE-AUG26 | T13: Multistate report, Aug. 2026
A14: EVT-0013 | C14: 2027-session | D14: Oregon | E14: OR | F14: State | H14: Forward Catalyst | I14: Political & Regulatory | J14: Expected | K14: Negative | L14: High | M14: Moratorium proposal and incentive framework return to legislature | N14: Legislators announced a three-year moratorium proposal while enterprise-zone eligibility remains paused pending the 2027 session. | O14: Political & Regulatory | Q14: ↓ | R14: HIGH | S14: SRC-MULTISTATE-AUG26 | T14: Multistate report, Aug. 2026

Sheet Sources
A1: Source ID | B1: Source Name | C1: Source Type | D1: Publisher / Organization | E1: Source Date | F1: Scope | G1: File / URL | H1: Citation / Locator | I1: States / Counties Covered | J1: Last Verified | K1: Notes

Sheet Change Log
A1: Change ID | B1: Date | C1: State / County | D1: Record Type | E1: Dimension / Field | F1: Old Value | G1: New Value | H1: Reason | I1: Event ID | J1: Source ID | K1: Analyst | L1: Published? | M1: Notes
A2: CHG-0001 | B2: 46277 | C2: Alabama | D2: State | E2: Overall Score | G2: 74 | H2: Initial migration into STACK Policy Master v1 | L2: Yes | M2: Migrated from v0.6.1 production JSON
A3: CHG-0002 | B3: 46277 | C3: Alaska | D3: State | E3: Overall Score | G3: 64 | H3: Initial migration into STACK Policy Master v1 | L3: Yes | M3: Migrated from v0.6.1 production JSON
A4: CHG-0003 | B4: 46277 | C4: Arizona | D4: State | E4: Overall Score | G4: 46 | H4: Initial migration into STACK Policy Master v1 | L4: Yes | M4: Migrated from v0.6.1 production JSON
A5: CHG-0004 | B5: 46277 | C5: Arkansas | D5: State | E5: Overall Score | G5: 80 | H5: Initial migration into STACK Policy Master v1 | L5: Yes | M5: Migrated from v0.6.1 production JSON
A6: CHG-0005 | B6: 46277 | C6: California | D6: State | E6: Overall Score | G6: 34 | H6: Initial migration into STACK Policy Master v1 | L6: Yes | M6: Migrated from v0.6.1 production JSON
A7: CHG-0006 | B7: 46277 | C7: Colorado | D7: State | E7: Overall Score | G7: 42 | H7: Initial migration into STACK Policy Master v1 | L7: Yes | M7: Migrated from v0.6.1 production JSON
A8: CHG-0007 | B8: 46277 | C8: Connecticut | D8: State | E8: Overall Score | G8: 56 | H8: Initial migration into STACK Policy Master v1 | L8: Yes | M8: Migrated from v0.6.1 production JSON
A9: CHG-0008 | B9: 46277 | C9: Delaware | D9: State | E9: Overall Score | G9: 56 | H9: Initial migration into STACK Policy Master v1 | L9: Yes | M9: Migrated from v0.6.1 production JSON
A10: CHG-0009 | B10: 46277 | C10: Florida | D10: State | E10: Overall Score | G10: 60 | H10: Initial migration into STACK Policy Master v1 | L10: Yes | M10: Migrated from v0.6.1 production JSON
A11: CHG-0010 | B11: 46277 | C11: Georgia | D11: State | E11: Overall Score | G11: 64 | H11: Initial migration into STACK Policy Master v1 | L11: Yes | M11: Migrated from v0.6.1 production JSON
A12: CHG-0011 | B12: 46277 | C12: Hawaii | D12: State | E12: Overall Score | G12: 54 | H12: Initial migration into STACK Policy Master v1 | L12: Yes | M12: Migrated from v0.6.1 production JSON
A13: CHG-0012 | B13: 46277 | C13: Idaho | D13: State | E13: Overall Score | G13: 76 | H13: Initial migration into STACK Policy Master v1 | L13: Yes | M13: Migrated from v0.6.1 production JSON
... A51: CHG-0050 | B51: 46277 | C51: Wyoming | D51: State | E51: Overall Score | G51: 88 | H51: Initial migration into STACK Policy Master v1 | L51: Yes | M51: Migrated from v0.6.1 production JSON

Sheet Methodology
A1: STACK POLICY SCORE v2.0 | B1: Balanced Development Model
A2: Dimension | B2: Weight
A3: Power & Energy | B3: 0.35
A4: Water | B4: 0.15
A5: Policy & Regulatory Environment | B5: 0.25
A6: Community Sentiment | B6: 0.25
A7: Scoring | B7: 1.0–5.0, half-point increments
A8: Formula | B8: 20 × (0.35×Power + 0.15×Water + 0.25×Policy + 0.25×Community)
A9: Calibration status | B9: Provisional crosswalk; NOT an independently evidence-reviewed rescoring
A10: Power | B10: Existing Power & Energy score used as starting proxy. Speed-to-power timelines need utility-level validation.
A11: Water | B11: Existing Water & Environmental score used as starting proxy; environmental issues need reassignment.
A12: Policy | B12: Starting proxy = average of prior Incentives & Tax and Political & Regulatory. Local zoning/moratoria should be moved here during review.
A13: Community | B13: Starting proxy = prior Local score. This includes entitlement constraints, so not yet a pure sentiment measure. HeatMap index not converted automatically.
A14: Critical Constraint | B14: Separate flag; do not let weighted average hide binding development blocks.
A15: Historical baseline | B15: Original State Scores sheet preserved unchanged.
A16: Review priority | B16: Validate state by state before publishing scores as finalized.

Sheet HeatMap Evidence Oct 2026
A1: STACK COMMUNITY SENTIMENT | HEATMAP EVIDENCE LOG | B1: Captured 2026-10-20
A2: Source | B2: HeatMap Pro screenshots provided in conversation; not a structured data export
A3: Scope | B3: National county-level opposition map; data-center-only contested projects filtered by cancelled / pending / approved; national data-center dashboard
A4: Interpretation | B4: Visual evidence only. No state counts, cancellation rates, or numeric HeatMap county indices extracted.
A5: Scoring treatment | B5: Maintain existing provisional Community scores until county data / project denominators or independent case validation.
A6: Dashboard context | B6: Data-center filtered dashboard shows rising contested-project activity and cancellations; charts do not establish causal cancellation reasons or state-level rates.
A8: State / market | B8: Visible evidence / observation | C8: Status | D8: Scoring implication | E8: Confidence
A9: Virginia / DC corridor | B9: Dense contested activity visible across outcome views; active development and contested approvals coexist. | C9: Mixed outcomes | D9: Review Community score; do not infer rejection rate. | E9: Low — visual
A10: Maryland / Pennsylvania | B10: Contested project activity across Mid-Atlantic; policy report independently lists local moratoria. | C10: Mixed outcomes | D10: Check county-specific project histories before scoring. | E10: Low — visual
A11: Ohio / Indiana / Illinois / Michigan | B11: Multiple contested projects, including cancelled, pending and approved, across Midwest. | C11: Mixed outcomes | D11: Prioritize targeted verification in core markets. | E11: Low — visual
A12: Georgia / Carolinas | B12: Clusters of contested data-center projects with varied outcomes. | C12: Mixed outcomes | D12: Review development corridors and local action separately. | E12: Low — visual
A13: Texas | B13: Contested projects across DFW and central Texas; outcomes vary. | C13: Mixed outcomes | D13: Avoid statewide generalization; prioritize key markets. | E13: Low — visual
A14: Arizona / California | B14: Scattered contested projects; opposition-risk map has notable geographic variation. | C14: Mixed outcomes | D14: County-based review required. | E14: Low — visual
A15: Pacific Northwest | B15: Contested activity concentrated in selected corridors. | C15: Mixed outcomes | D15: Do not equate sparse markers with supportive sentiment. | E15: Low — visual
A16: Mountain West / Plains | B16: Generally fewer visible contested project markers in several states. | C16: Limited visible coverage | D16: Low activity is not evidence of acceptance. | E16: Low — visual
A18: Methodology | B18: Opposition index 50%; contested project activity/outcomes 35%; demonstrated acceptance 15% — proposed internal components, not calculated from these screenshots.
A19: Critical limitations | B19: Data Center Risk map is labeled Less/More Opposition, but underlying formula unknown. National map screenshots cannot support precise 50-state values.
A20: Next validation | B20: Seek HeatMap county export or project-level records; capture project totals and status outcomes by state; validate cancellation causes; weight relevant development markets.
